pymem/__init__.py
pymem/exception.py
pymem/memory.py
pymem/pattern.py
pymem/process.py
pymem/ptypes.py
pymem/thread.py
pymem/ressources/__init__.py
pymem/ressources/advapi32.py
pymem/ressources/kernel32.py
pymem/ressources/ntdll.py
pymem/ressources/psapi.py
pymem/ressources/structure.py
Pymem-1.13.1.dist-info/AUTHORS
Pymem-1.13.1.dist-info/LICENSE
Pymem-1.13.1.dist-info/METADATA
Pymem-1.13.1.dist-info/WHEEL
Pymem-1.13.1.dist-info/top_level.txt
Pymem-1.13.1.dist-info/RECORD
