Metadata-Version: 2.1
Name: Pymem
Version: 1.13.1
Summary: pymem: python memory access made easy
Home-page: http://pymem.readthedocs.org/en/latest/
Author: Fabien Reboia
Author-email: srounet@gmail.com
Maintainer: Fabien Reboia
Maintainer-email: srounet@gmail.com
License: mit
Keywords: memory win32 windows process
Platform: windows
Classifier: Programming Language :: Python :: 3.8
Classifier: Programming Language :: Python :: 3.9
Classifier: Programming Language :: Python :: 3.10
Classifier: Programming Language :: Python :: 3.11
Classifier: Programming Language :: Python :: 3.12
Classifier: Environment :: Win32 (MS Windows)
Classifier: Intended Audience :: Developers
Classifier: License :: OSI Approved :: MIT License
Provides-Extra: doc
Requires-Dist: recommonmark ==0.7.1 ; extra == 'doc'
Requires-Dist: sphinx ==4.4.0 ; extra == 'doc'
Requires-Dist: sphinx-rtd-theme ==1.0.0 ; extra == 'doc'
Provides-Extra: speed
Requires-Dist: regex ; extra == 'speed'
Provides-Extra: test
Requires-Dist: codecov ; extra == 'test'
Requires-Dist: pytest ; extra == 'test'
Requires-Dist: pytest-cov ; extra == 'test'
Requires-Dist: twine ; extra == 'test'
